as_scraper_airflow/__init__.py
as_scraper_airflow/errors.py
as_scraper_airflow/operators/__init__.py
as_scraper_airflow/operators/scraper.py
as_scraper_airflow/operators/scraper_to_bq.py
as_scraper_airflow/operators/scraper_to_logs.py
as_scraper_airflow-1.2.0.dist-info/LICENSE
as_scraper_airflow-1.2.0.dist-info/METADATA
as_scraper_airflow-1.2.0.dist-info/WHEEL
as_scraper_airflow-1.2.0.dist-info/top_level.txt
as_scraper_airflow-1.2.0.dist-info/RECORD
