Metadata-Version: 2.1
Name: as-scraper-airflow
Version: 1.2.0
Summary: Python library for scraping inside Airflow.
Home-page: https://github.com/Avila-Systems/as-scraper-airflow
Author: Alvaro Avila
Author-email: almiavicas@gmail.com
Project-URL: Github Project, https://github.com/Avila-Systems/as-scraper-airflow
Project-URL: Issue Tracker, https://github.com/Avila-Systems/as-scraper-airflow/issues
Classifier: Intended Audience :: Developers
Classifier: Programming Language :: Python
Classifier: Programming Language :: Python :: 3
Classifier: Operating System :: POSIX
Classifier: License :: OSI Approved :: MIT License
Classifier: Topic :: Software Development :: Libraries
Requires-Python: >=3.6
License-File: LICENSE
Requires-Dist: apache-airflow (>=2.2.3)
Requires-Dist: apache-airflow-providers-google
Requires-Dist: as-scraper
